{
    "os": "Linux-6.8.0-49-generic-x86_64-with-glibc2.35",
    "python": "3.12.3",
    "heartbeatAt": "2024-12-26T13:57:16.877540",
    "startedAt": "2024-12-26T13:57:16.299887",
    "docker": null,
    "cuda": null,
    "args": [
        "is_debug=true",
        "training.epochs=1",
        "experiment_type=normal",
        "model_name=tohoku-nlp/bert-base-japanese-v3"
    ],
    "state": "running",
    "program": "/home/takuma-s/Desktop/discourse_relation_explainability/src/fine_tuning.py",
    "codePathLocal": "src/fine_tuning.py",
    "codePath": "src/fine_tuning.py",
    "git": {
        "remote": "https://github.com/takuma1229/discourse_relation_explainability.git",
        "commit": "c4e5d4941f16da3fe763e00aff6905bb6afe31bf"
    },
    "email": "takuma1229tennis@gmail.com",
    "root": "/home/takuma-s/Desktop/discourse_relation_explainability",
    "host": "takuma-s",
    "username": "takuma-s",
    "executable": "/home/takuma-s/Desktop/discourse_relation_explainability/.venv/bin/python",
    "cpu_count": 20,
    "cpu_count_logical": 28,
    "cpu_freq": {
        "current": 1034.3279285714286,
        "min": 800.0,
        "max": 4842.857142857143
    },
    "cpu_freq_per_core": [
        {
            "current": 1099.988,
            "min": 800.0,
            "max": 5300.0
        },
        {
            "current": 800.0,
            "min": 800.0,
            "max": 5300.0
        },
        {
            "current": 1801.958,
            "min": 800.0,
            "max": 5300.0
        },
        {
            "current": 800.0,
            "min": 800.0,
            "max": 5300.0
        },
        {
            "current": 800.0,
            "min": 800.0,
            "max": 5300.0
        },
        {
            "current": 800.0,
            "min": 800.0,
            "max": 5300.0
        },
        {
            "current": 3039.485,
            "min": 800.0,
            "max": 5300.0
        },
        {
            "current": 800.0,
            "min": 800.0,
            "max": 5300.0
        },
        {
            "current": 1100.0,
            "min": 800.0,
            "max": 5400.0
        },
        {
            "current": 800.0,
            "min": 800.0,
            "max": 5400.0
        },
        {
            "current": 798.887,
            "min": 800.0,
            "max": 5400.0
        },
        {
            "current": 800.0,
            "min": 800.0,
            "max": 5400.0
        },
        {
            "current": 800.0,
            "min": 800.0,
            "max": 5300.0
        },
        {
            "current": 800.0,
            "min": 800.0,
            "max": 5300.0
        },
        {
            "current": 800.0,
            "min": 800.0,
            "max": 5300.0
        },
        {
            "current": 800.0,
            "min": 800.0,
            "max": 5300.0
        },
        {
            "current": 800.0,
            "min": 800.0,
            "max": 4200.0
        },
        {
            "current": 950.45,
            "min": 800.0,
            "max": 4200.0
        },
        {
            "current": 800.243,
            "min": 800.0,
            "max": 4200.0
        },
        {
            "current": 1128.77,
            "min": 800.0,
            "max": 4200.0
        },
        {
            "current": 989.19,
            "min": 800.0,
            "max": 4200.0
        },
        {
            "current": 1282.777,
            "min": 800.0,
            "max": 4200.0
        },
        {
            "current": 800.0,
            "min": 800.0,
            "max": 4200.0
        },
        {
            "current": 800.0,
            "min": 800.0,
            "max": 4200.0
        },
        {
            "current": 800.795,
            "min": 800.0,
            "max": 4200.0
        },
        {
            "current": 800.0,
            "min": 800.0,
            "max": 4200.0
        },
        {
            "current": 800.0,
            "min": 800.0,
            "max": 4200.0
        },
        {
            "current": 800.0,
            "min": 800.0,
            "max": 4200.0
        }
    ],
    "disk": {
        "/": {
            "total": 937.3305015563965,
            "used": 194.01257705688477
        }
    },
    "gpu": "NVIDIA GeForce RTX 4060 Ti",
    "gpu_count": 1,
    "gpu_devices": [
        {
            "name": "NVIDIA GeForce RTX 4060 Ti",
            "memory_total": 17175674880
        }
    ],
    "memory": {
        "total": 31.05651092529297
    }
}
